asg_scaler_lambda/asg_helper.py
asg_scaler_lambda/asg_scaler.py
asg_scaler_lambda/codepipeline_event.py
asg_scaler_lambda-0.1.1.dist-info/LICENSE
asg_scaler_lambda-0.1.1.dist-info/METADATA
asg_scaler_lambda-0.1.1.dist-info/WHEEL
asg_scaler_lambda-0.1.1.dist-info/entry_points.txt
asg_scaler_lambda-0.1.1.dist-info/RECORD
