Metadata-Version: 2.1
Name: asg-scaler-lambda
Version: 0.1.1
Summary: Scales ASGs and authorises CodePipeline
Home-page: https://github.com/XargsUK/asg-scaler-lambda
License: MIT
Keywords: aws,lambda,asg,autoscaling,codepipeline,codedeploy,scaling
Author: XargsUK
Author-email: 51077147+XargsUK@users.noreply.github.com
Maintainer: XargsUK
Maintainer-email: 51077147+XargsUK@users.noreply.github.com
Requires-Python: >=3.8.1,<4.0.0
Classifier: Development Status :: 4 - Beta
Classifier: Intended Audience :: Developers
Classifier: License :: OSI Approved :: MIT License
Classifier: Operating System :: OS Independent
Classifier: Programming Language :: Python :: 3
Classifier: Programming Language :: Python :: 3.9
Classifier: Programming Language :: Python :: 3.10
Classifier: Programming Language :: Python :: 3.11
Classifier: Programming Language :: Python :: 3.12
Classifier: Programming Language :: Python :: 3.8
Classifier: Topic :: Software Development :: Libraries
Classifier: Topic :: Utilities
Requires-Dist: boto3 (>=1.30,<2.0)
Project-URL: Repository, https://github.com/XargsUK/asg-scaler-lambda
